mamushi/__init__.py
mamushi/__main__.py
mamushi/__version__.py
mamushi/formatting/__init__.py
mamushi/formatting/brackets.py
mamushi/formatting/comments.py
mamushi/formatting/format.py
mamushi/formatting/linegen.py
mamushi/formatting/lines.py
mamushi/formatting/nodes.py
mamushi/formatting/strings.py
mamushi/formatting/whitespace.py
mamushi/parsing/__init__.py
mamushi/parsing/comparator.py
mamushi/parsing/grammar.lark
mamushi/parsing/indenter.py
mamushi/parsing/parser.py
mamushi/parsing/pytree.py
mamushi/parsing/tokens.py
mamushi/utils/__init__.py
mamushi/utils/files.py
mamushi/utils/output.py
mamushi/utils/report.py
mamushi-0.0.8.dist-info/licenses/LICENSE
mamushi-0.0.8.dist-info/METADATA
mamushi-0.0.8.dist-info/WHEEL
mamushi-0.0.8.dist-info/entry_points.txt
mamushi-0.0.8.dist-info/top_level.txt
mamushi-0.0.8.dist-info/RECORD
