Metadata-Version: 2.4
Name: mamushi
Version: 0.0.8
Summary: Vyper formatter
Home-page: https://github.com/benber86/mamushi
License: { text = "MIT" }
Project-URL: Source, https://github.com/benber86/mamushi
Project-URL: Tracker, https://github.com/benber86/mamushi/issues
Classifier: Development Status :: 4 - Beta
Classifier: Environment :: Console
Classifier: Intended Audience :: Developers
Classifier: License :: OSI Approved :: MIT License
Classifier: Natural Language :: English
Classifier: Operating System :: OS Independent
Classifier: Programming Language :: Python :: 3 :: Only
Classifier: Programming Language :: Python :: 3.9
Classifier: Programming Language :: Python :: 3.10
Classifier: Programming Language :: Python :: 3.11
Classifier: Programming Language :: Python :: 3.12
Classifier: Programming Language :: Python :: 3.13
Classifier: Topic :: Software Development :: Quality Assurance
Requires-Python: >=3.9
License-File: LICENSE
Requires-Dist: click==8.1.3
Requires-Dist: pathspec>=0.9.0
Requires-Dist: lark>=1.0.0
Requires-Dist: mypy-extensions>=1.1.0
Provides-Extra: dev
Requires-Dist: black==25.1.0; extra == "dev"
Requires-Dist: pre-commit==2.20.0; extra == "dev"
Requires-Dist: mypy-extensions>=1.1.0; extra == "dev"
Requires-Dist: mypy>=0.900; extra == "dev"
Requires-Dist: flake8==7.2.0; extra == "dev"
Requires-Dist: pylint==2.14.5; extra == "dev"
Requires-Dist: pytest>=6.0.0; extra == "dev"
Requires-Dist: pytest-cov>=3.0.0; extra == "dev"
Requires-Dist: coverage>=6.0.0; extra == "dev"
Requires-Dist: bump2version>=1.0.0; extra == "dev"
Dynamic: license-file
